hello_world/__init__.py
hello_world/tools/__init__.py
hello_world/tools/hello_world_tool.py
hello_world/tools/my_tool.py
hello_world/tools/utils.py
hello_world/yamls/hello_world_tool.yaml
hello_world/yamls/my_tool.yaml
tests/__init__.py
tests/test_hello_world_tool.py
yao_test_package-0.0.1.dist-info/METADATA
yao_test_package-0.0.1.dist-info/WHEEL
yao_test_package-0.0.1.dist-info/entry_points.txt
yao_test_package-0.0.1.dist-info/top_level.txt
yao_test_package-0.0.1.dist-info/RECORD
